sprintify/__init__.py
sprintify/navigation/__init__.py
sprintify/navigation/navigation_widget.py
sprintify/navigation/colors/__init__.py
sprintify/navigation/colors/modes.py
sprintify/navigation/colors/palette.py
sprintify/navigation/rulers/__init__.py
sprintify/navigation/rulers/base.py
sprintify/navigation/rulers/item.py
sprintify/navigation/rulers/number.py
sprintify/navigation/rulers/timeline.py
sprintify/navigation/widgets/__init__.py
sprintify/navigation/widgets/drawing_widget.py
sprintify/navigation/widgets/item_ruler_widget.py
sprintify/navigation/widgets/number_ruler_widget.py
sprintify/navigation/widgets/timeline_ruler_widget.py
sprintify_navigation-1.0.14.dist-info/licenses/LICENSE
sprintify_navigation-1.0.14.dist-info/METADATA
sprintify_navigation-1.0.14.dist-info/WHEEL
sprintify_navigation-1.0.14.dist-info/top_level.txt
sprintify_navigation-1.0.14.dist-info/RECORD
