Metadata-Version: 2.4
Name: sprintify-navigation
Version: 1.0.14
Summary: A navigation widget  based on PySide6
Home-page: https://github.com/sspjuth/sprintify
Author: Sami Spjuth
Author-email: sami@spjuth.org
Classifier: Development Status :: 4 - Beta
Classifier: Intended Audience :: Developers
Classifier: License :: OSI Approved :: MIT License
Classifier: Programming Language :: Python :: 3
Classifier: Programming Language :: Python :: 3.9
Requires-Python: >=3.6
License-File: LICENSE
Requires-Dist: PySide6==6.7.1
Requires-Dist: numpy
Dynamic: author
Dynamic: author-email
Dynamic: classifier
Dynamic: description
Dynamic: description-content-type
Dynamic: home-page
Dynamic: license-file
Dynamic: requires-dist
Dynamic: requires-python
Dynamic: summary
